hsuanwuhub/__init__.py
hsuanwuhub/train.py
hsuanwuhub/cfgs/config.yaml
hsuanwuhub/cfgs/task/daac_procgen.yaml
hsuanwuhub/cfgs/task/drqv2_dmc_pixel.yaml
hsuanwuhub/cfgs/task/impala_atari.yaml
hsuanwuhub/cfgs/task/ppg_procgen.yaml
hsuanwuhub/cfgs/task/ppo_atari.yaml
hsuanwuhub/cfgs/task/ppo_bullet.yaml
hsuanwuhub/cfgs/task/ppo_procgen.yaml
hsuanwuhub/cfgs/task/sac_dmc_state.yaml
hsuanwuhub/datasets/__init__.py
hsuanwuhub/datasets/procgen.py
hsuanwuhub-0.0.1b2.dist-info/METADATA
hsuanwuhub-0.0.1b2.dist-info/WHEEL
hsuanwuhub-0.0.1b2.dist-info/licenses/LICENSE
hsuanwuhub-0.0.1b2.dist-info/RECORD
