Metadata-Version: 2.1
Name: hsuanwuhub
Version: 0.0.1b2
Summary: Model Hub of the Long-Term Evolution Project of Reinforcement Learning
Project-URL: Code, https://github.com/RLE-Foundation/HsuanwuHub
Project-URL: Documentation, https://docs.hsuanwu.dev/
Project-URL: Benchmark, https://hub.hsuanwu.dev/
Project-URL: Bug Tracker, https://github.com/RLE-Foundation/HsuanwuHub/issues
Author-email: Reinforcement Learning Evolution Foundation <hsuanwudev@gmail.com>
License-File: LICENSE
Keywords: Algorithm,Baseline,Datasets,Evolution,Hub,Models,Reinforcement Learning
Classifier: License :: OSI Approved :: MIT License
Classifier: Operating System :: OS Independent
Classifier: Programming Language :: Python :: 3
Requires-Python: >=3.8
Requires-Dist: hsuanwu
Requires-Dist: huggingface-hub
Requires-Dist: numpy
Requires-Dist: pandas
